qt5_cef-0.0.6.dist-info/METADATA
qt5_cef-0.0.6.dist-info/RECORD
qt5_cef-0.0.6.dist-info/WHEEL
qt5_cef-0.0.6.dist-info/top_level.txt
webview/__init__.py
webview/burgeon.cef.sdk.js
webview/constant.py
webview/qt.py
