Metadata-Version: 2.1
Name: qt5-cef
Version: 0.0.6
Summary: A simple tool kit for create desktop application
Home-page: https://github.com/hycool/pywebview
Author: hy
Author-email: hycool.happy@163.com
License: UNKNOWN
Platform: UNKNOWN
Classifier: Programming Language :: Python :: 3
Classifier: License :: OSI Approved :: MIT License
Classifier: Operating System :: OS Independent
Requires-Dist: PyQt5 (==5.11.2)
Requires-Dist: cefpython3 (==57.1)
